supervisedML.py
supervisedML-0.0.5.dist-info/LICENCE
supervisedML-0.0.5.dist-info/METADATA
supervisedML-0.0.5.dist-info/WHEEL
supervisedML-0.0.5.dist-info/top_level.txt
supervisedML-0.0.5.dist-info/RECORD
