Metadata-Version: 2.1
Name: supervisedML
Version: 0.0.5
Summary: machine learning supervised models for python with accuracy metrics
Author-email: Mohga Emam <mohgasolimanemam@gmail.com>
Project-URL: Homepage, https://github.com/pypa/sampleproject
Project-URL: Bug Tracker, https://github.com/pypa/sampleproject/issues
Classifier: Programming Language :: Python :: 3
Classifier: License :: OSI Approved :: MIT License
Classifier: Operating System :: OS Independent
Requires-Python: >=3.7
License-File: LICENCE
